setup.py
BiNPr_distributions/Binomialdistribution.py
BiNPr_distributions/Gaussiandistribution.py
BiNPr_distributions/Generaldistribution.py
BiNPr_distributions/__init__.py
BiNPr_distributions.egg-info/PKG-INFO
BiNPr_distributions.egg-info/SOURCES.txt
BiNPr_distributions.egg-info/dependency_links.txt
BiNPr_distributions.egg-info/not-zip-safe
BiNPr_distributions.egg-info/top_level.txt