Metadata-Version: 1.0
Name: BiNPr-distributions
Version: 1.3
Summary: Gaussian and Binomial probability distributions
Home-page: UNKNOWN
Author: Ahmed Md
Author-email: freda31k@gmail.com
License: UNKNOWN
Platform: UNKNOWN
